lolcatt/.githash
lolcatt/__init__.py
lolcatt/app.py
lolcatt/cli.py
lolcatt/casting/__init__.py
lolcatt/casting/caster.py
lolcatt/casting/youtube_playlist_handler.py
lolcatt/ui/__init__.py
lolcatt/ui/lolcatt.tcss
lolcatt/ui/lolcatt_controls.py
lolcatt/ui/lolcatt_device_info.py
lolcatt/ui/lolcatt_devicelist.py
lolcatt/ui/lolcatt_playback_info.py
lolcatt/ui/lolcatt_playlist.py
lolcatt/ui/lolcatt_progress.py
lolcatt/ui/lolcatt_url_input.py
lolcatt/utils/__init__.py
lolcatt/utils/utils.py
lolcatt-0.5.1.dist-info/LICENSE
lolcatt-0.5.1.dist-info/METADATA
lolcatt-0.5.1.dist-info/WHEEL
lolcatt-0.5.1.dist-info/entry_points.txt
lolcatt-0.5.1.dist-info/top_level.txt
lolcatt-0.5.1.dist-info/RECORD
