Metadata-Version: 2.1
Name: lolcatt
Version: 0.5.1
Summary: A TUI wrapper around `catt`.
Home-page: https://github.com/LokiLuciferase/lolcatt
Author: Lukas Lüftinger
Author-email: lukas.lueftinger@outlook.com
License: MIT license
Keywords: lolcatt
Classifier: Development Status :: 2 - Pre-Alpha
Classifier: Intended Audience :: Developers
Classifier: License :: OSI Approved :: MIT License
Classifier: Natural Language :: English
Classifier: Programming Language :: Python :: 3
Classifier: Programming Language :: Python :: 3.8
Classifier: Programming Language :: Python :: 3.9
Classifier: Programming Language :: Python :: 3.10
Requires-Python: >=3.8
License-File: LICENSE
Requires-Dist: toml
Requires-Dist: click >=8
Requires-Dist: yt-dlp >=2024.11.18
Requires-Dist: textual <=0.85
Requires-Dist: catt
